[
  {
    "Name": "TestGroup1",
    "Label": "Test group 1",
    "Order": 1,
    "Items": [
      {
        "Name": "Item1",
        "Label": "Item 1",
        "Type": 1,
        "Address": "https://localhost:7001/hc"
      },
      {
        "Name": "Item2",
        "Label": "Item 2",
        "Type": 2,
        "Address": "https://localhost:8001"
      },
      {
        "Name": "Item3",
        "Label": "Item 3",
        "Type": 3,
        "Address": "net.tcp://localhost:9001/TestService/hc"
      }
    ]
  },
  {
    "Name": "TestGroup2",
    "Label": "Test group 2",
    "Order": 1,
    "Items": [
      {
        "Name": "Item21",
        "Label": "Item 21",
        "Type": 1,
        "Address": "https://localhost:7001/hc"
      },
      {
        "Name": "Item22",
        "Label": "Item 22",
        "Type": 1,
        "Address": "https://localhost:7001/hc"
      },
      {
        "Name": "Item23",
        "Label": "Item 23",
        "Type": 1,
        "Address": "https://localhost:7001/hc"
      }
    ]
  }
]